assets/teda.desktop
assets/teda.svg
teda/__init__.py
teda/command_line.py
teda/console.py
teda/desktop_install.py
teda/draggingComponent.py
teda/fitsopen.py
teda/fitting.py
teda/help_content.py
teda/icons/1-2-24px.svg
teda/icons/1-4-24px.svg
teda/icons/add_circle_outline-24px.svg
teda/icons/autopause-24px.svg
teda/icons/autopause_disabled-24px.svg
teda/icons/calendar_view_week-24px.svg
teda/icons/circle-24px.svg
teda/icons/count1-24px.svg
teda/icons/count2-24px.svg
teda/icons/count3-24px.svg
teda/icons/count4-24px.svg
teda/icons/count5-24px.svg
teda/icons/delete_forever-24px.svg
teda/icons/file-earmark-plus.svg
teda/icons/filter_alt-24px.svg
teda/icons/folder-24px.svg
teda/icons/home-24px.svg
teda/icons/house-24px.svg
teda/icons/insights-24px.svg
teda/icons/keyboard_arrow_left-24px.svg
teda/icons/keyboard_arrow_right-24px.svg
teda/icons/line_weight-24px.svg
teda/icons/new.png
teda/icons/not_started-24px.svg
teda/icons/note_add-24px.svg
teda/icons/panning-24px.svg
teda/icons/pause_circle_outline-24px.svg
teda/icons/photo_filter-24px.svg
teda/icons/play_circle_outline-24px.svg
teda/icons/push_pin-24px.svg
teda/icons/question_mark-24px.svg
teda/icons/refresh-24px.svg
teda/icons/save-24px.svg
teda/icons/skip_next-24px.svg
teda/icons/skip_previous-24px.svg
teda/icons/slider-24px.svg
teda/icons/sort-24px.svg
teda/icons/stop_circle-24px.svg
teda/icons/teda-24px.svg
teda/icons/timeline-24px.svg
teda/icons/x2-24px.svg
teda/icons/x4-24px.svg
teda/icons.py
teda/img/akondastro_logo_dark.svg
teda/img/teda.svg
teda/models/__init__.py
teda/models/cmaps.py
teda/models/coordinates.py
teda/models/scalesModel.py
teda/painterComponent.py
teda/painterShapes/CircleCenterShape.py
teda/painterShapes/__init__.py
teda/painterShapes/circleShape.py
teda/painterShapes/lineProfileShape.py
teda/painterShapes/rectangleMinatureShape.py
teda/teda_fits.py
teda/version.py
teda/viewer_mainwindow.py
teda/views/__init__.py
teda/views/fitsplot.py
teda/views/fitsplot_fitsfile.py
teda-4.0.3.dist-info/LICENSE
teda-4.0.3.dist-info/METADATA
teda-4.0.3.dist-info/WHEEL
teda-4.0.3.dist-info/entry_points.txt
teda-4.0.3.dist-info/RECORD
