Metadata-Version: 2.1
Name: teda
Version: 4.0.3
Summary: Yet Another FITS Viewer
License: MIT
Author: majkelx
Author-email: mkalusz@camk.edu.pl
Requires-Python: >=3.9,<3.14
Classifier: License :: OSI Approved :: MIT License
Classifier: Programming Language :: Python :: 3
Classifier: Programming Language :: Python :: 3.9
Classifier: Programming Language :: Python :: 3.10
Classifier: Programming Language :: Python :: 3.11
Classifier: Programming Language :: Python :: 3.12
Provides-Extra: console
Provides-Extra: watchdog
Requires-Dist: astropy (>5.2.2)
Requires-Dist: matplotlib (>=3.7.1,<4.0.0)
Requires-Dist: numpy (<2.0)
Requires-Dist: pyside6 (>=6.8.0.2,<7.0.0.0)
Requires-Dist: qtconsole (>=5.4.4,<6.0.0) ; extra == "console"
Requires-Dist: scipy (>=1.10.1,<2.0.0)
Requires-Dist: traitlets (>=5.9.0,<6.0.0)
Requires-Dist: watchdog (>=3.0.0,<4.0.0) ; extra == "watchdog"
